rest_model_service/__init__.py
rest_model_service/configuration.py
rest_model_service/exception_handlers.py
rest_model_service/generate_openapi.py
rest_model_service/helpers.py
rest_model_service/main.py
rest_model_service/routes.py
rest_model_service/schemas.py
rest_model_service/status_manager.py
rest_model_service/version.txt
rest_model_service-0.6.0.dist-info/LICENSE
rest_model_service-0.6.0.dist-info/METADATA
rest_model_service-0.6.0.dist-info/WHEEL
rest_model_service-0.6.0.dist-info/entry_points.txt
rest_model_service-0.6.0.dist-info/top_level.txt
rest_model_service-0.6.0.dist-info/RECORD
