Metadata-Version: 2.1
Name: rest_model_service
Version: 0.6.0
Summary: RESTful service for hosting machine learning models.
Home-page: https://github.com/schmidtbri/rest-model-service
Author: Brian Schmidt
Author-email: 6666331+schmidtbri@users.noreply.github.com
License: BSD
Project-URL: Documentation, https://schmidtbri.github.io/rest-model-service/
Project-URL: Source Code, https://github.com/schmidtbri/rest-model-service
Project-URL: Tracker, https://github.com/schmidtbri/rest-model-service/issues
Keywords: machine learning,REST,service,model deployment
Classifier: Programming Language :: Python :: 3.8
Classifier: Programming Language :: Python :: 3.9
Classifier: Programming Language :: Python :: 3.10
Classifier: Programming Language :: Python :: 3.11
Classifier: Intended Audience :: Developers
Classifier: Operating System :: OS Independent
Requires-Python: >=3.7
License-File: LICENSE
Requires-Dist: ml-base >=0.2.0
Requires-Dist: fastapi
Requires-Dist: uvicorn
Requires-Dist: pyyaml
Provides-Extra: metrics
Requires-Dist: prometheus-fastapi-instrumentator ; extra == 'metrics'
